cs_conduit_jupyter_kernel_provisioner-0.1.1.dist-info/licenses/LICENSE
cspyk/__init__.py
cspyk/devtunnel.py
cspyk/kernelapp.py
cspyk/provisioning.py
cspyk/provisioning_local.py
cs_conduit_jupyter_kernel_provisioner-0.1.1.dist-info/METADATA
cs_conduit_jupyter_kernel_provisioner-0.1.1.dist-info/WHEEL
cs_conduit_jupyter_kernel_provisioner-0.1.1.dist-info/entry_points.txt
cs_conduit_jupyter_kernel_provisioner-0.1.1.dist-info/top_level.txt
cs_conduit_jupyter_kernel_provisioner-0.1.1.dist-info/RECORD
