Metadata-Version: 2.4
Name: cs-conduit-jupyter-kernel-provisioner
Version: 0.1.1
Summary: Jupyter kernel provisioner package for Cybershuttle Conduit
Author: Dimuthu Wannipurage
License: Apache-2
Classifier: Topic :: Utilities
Classifier: Framework :: Jupyter
Requires-Python: >=3.10
License-File: LICENSE
Requires-Dist: jupyter-client>=8.7.0
Dynamic: license-file
